certiv/__init__.py
certiv/certiv.py
certiv/heartbeat.py
certiv/logger.py
certiv/shutdown.py
certiv/traffic_handler.py
certiv/api/__init__.py
certiv/api/auth.py
certiv/api/client.py
certiv/api/types.py
certiv/batch/__init__.py
certiv/batch/adapter.py
certiv/batch/manager.py
certiv/interceptor/__init__.py
certiv/interceptor/http_interceptor.py
certiv/interceptor/types.py
certiv/interceptor/patcher/__init__.py
certiv/interceptor/patcher/httpx_patcher.py
certiv/interceptor/patcher/parse.py
certiv/interceptor/patcher/requests_patcher.py
certiv/policy/__init__.py
certiv/policy/base.py
certiv/policy/registry.py
certiv/policy/handler/__init__.py
certiv/policy/handler/allow.py
certiv/policy/handler/block.py
certiv/policy/handler/block_graceful.py
certiv/policy/handler/pause.py
certiv/provider/__init__.py
certiv/provider/registry.py
certiv/provider/types.py
certiv/provider/llm/__init__.py
certiv/provider/llm/anthropic.py
certiv/provider/llm/google.py
certiv/provider/llm/openai.py
certiv/remote_exec/__init__.py
certiv/remote_exec/function_patcher.py
certiv/remote_exec/parser/__init__.py
certiv/remote_exec/parser/function_import_analyzer.py
certiv/remote_exec/parser/function_serializer.py
certiv/remote_exec/parser/requirements_resolver.py
certiv/tool/__init__.py
certiv/tool/core.py
certiv/tool/default.py
certiv/tool/langchain.py
certiv/tool/types.py
certiv-3.1.0.dist-info/licenses/LICENSE
certiv-3.1.0.dist-info/METADATA
certiv-3.1.0.dist-info/WHEEL
certiv-3.1.0.dist-info/top_level.txt
certiv-3.1.0.dist-info/RECORD
