Metadata-Version: 2.4
Name: certiv
Version: 3.1.0
Summary: Python client for Certiv (https://app.certiv.ai)
Author-email: Certiv Team <support@certiv.ai>
License: MIT
Project-URL: Homepage, https://certiv.ai
Classifier: Development Status :: 4 - Beta
Classifier: Intended Audience :: Developers
Classifier: Topic :: Software Development :: Libraries :: Python Modules
Classifier: Programming Language :: Python :: 3
Classifier: Programming Language :: Python :: 3.9
Classifier: Programming Language :: Python :: 3.10
Classifier: Programming Language :: Python :: 3.11
Classifier: Programming Language :: Python :: 3.12
Classifier: Programming Language :: Python :: 3.13
Requires-Python: >=3.9
License-File: LICENSE
Requires-Dist: pydantic>=2.12.3
Requires-Dist: httpx>=0.27.0
Requires-Dist: requests>=2.32.5
Requires-Dist: psutil>=7.1.2
Provides-Extra: langchain
Requires-Dist: langchain-core>=1.0.2; extra == "langchain"
Provides-Extra: dev
Requires-Dist: pytest>=8.4.2; extra == "dev"
Requires-Dist: pytest-cov>=7.0.0; extra == "dev"
Requires-Dist: black==25.9.0; extra == "dev"
Requires-Dist: flake8>=3.9.0; extra == "dev"
Requires-Dist: mypy>=1.18.2; extra == "dev"
Requires-Dist: ruff>=0.14.3; extra == "dev"
Requires-Dist: isort>=7.0.0; extra == "dev"
Provides-Extra: test
Requires-Dist: pytest>=8.4.2; extra == "test"
Requires-Dist: pytest-cov>=7.0.0; extra == "test"
Requires-Dist: openai>=2.6.1; extra == "test"
Requires-Dist: python-dotenv>=1.2.1; extra == "test"
Dynamic: license-file
